MANIFEST.in
requirements.txt
setup.py
slider.py
redis_memslider.egg-info/PKG-INFO
redis_memslider.egg-info/SOURCES.txt
redis_memslider.egg-info/dependency_links.txt
redis_memslider.egg-info/entry_points.txt
redis_memslider.egg-info/requires.txt
redis_memslider.egg-info/top_level.txt